spark_install.py
rstudio_spark_install-0.8.0.dist-info/DESCRIPTION.rst
rstudio_spark_install-0.8.0.dist-info/METADATA
rstudio_spark_install-0.8.0.dist-info/RECORD
rstudio_spark_install-0.8.0.dist-info/WHEEL
rstudio_spark_install-0.8.0.dist-info/metadata.json
rstudio_spark_install-0.8.0.dist-info/top_level.txt
