Metadata-Version: 2.0
Name: rstudio-spark-install
Version: 0.8.0
Summary: Utility to setup various versions of Apache Spark on multiple platforms.
Home-page: https://github.com/rstudio/spark-install
Author: Spark Installation authors
Author-email: authors@example.com
License: Apache
Keywords: Apache Spark PySpark Hadoop WinUtils
Platform: UNKNOWN
Classifier: Development Status :: 4 - Beta
Classifier: Intended Audience :: Developers
Classifier: Topic :: Software Development
Classifier: License :: OSI Approved :: Apache Software License
Classifier: Programming Language :: Python :: 2
Classifier: Programming Language :: Python :: 2.7
Classifier: Programming Language :: Python :: 3
Classifier: Programming Language :: Python :: 3.3
Classifier: Programming Language :: Python :: 3.4
Classifier: Programming Language :: Python :: 3.5
